benchbox/__init__.py
benchbox/amplab.py
benchbox/base.py
benchbox/clickbench.py
benchbox/coffeeshop.py
benchbox/datavault.py
benchbox/h2odb.py
benchbox/joinorder.py
benchbox/metadata_primitives.py
benchbox/nyctaxi.py
benchbox/read_primitives.py
benchbox/ssb.py
benchbox/tpcdi.py
benchbox/tpcds.py
benchbox/tpcds_obt.py
benchbox/tpch.py
benchbox/tpch_skew.py
benchbox/tpchavoc.py
benchbox/transaction_primitives.py
benchbox/tsbs_devops.py
benchbox/write_primitives.py
benchbox/_binaries/tpc-ds/darwin-arm64/checksums.md5
benchbox/_binaries/tpc-ds/darwin-arm64/dsdgen
benchbox/_binaries/tpc-ds/darwin-arm64/dsqgen
benchbox/_binaries/tpc-ds/darwin-arm64/tpcds.dst
benchbox/_binaries/tpc-ds/darwin-arm64/tpcds.idx
benchbox/_binaries/tpc-ds/darwin-arm64/query_templates/README
benchbox/_binaries/tpc-ds/darwin-arm64/query_templates/ansi.tpl
benchbox/_binaries/tpc-ds/darwin-arm64/query_templates/db2.tpl
benchbox/_binaries/tpc-ds/darwin-arm64/query_templates/netezza.tpl
benchbox/_binaries/tpc-ds/darwin-arm64/query_templates/oracle.tpl
benchbox/_binaries/tpc-ds/darwin-arm64/query_templates/query1.tpl
benchbox/_binaries/tpc-ds/darwin-arm64/query_templates/query10.tpl
benchbox/_binaries/tpc-ds/darwin-arm64/query_templates/query11.tpl
benchbox/_binaries/tpc-ds/darwin-arm64/query_templates/query12.tpl
benchbox/_binaries/tpc-ds/darwin-arm64/query_templates/query13.tpl
benchbox/_binaries/tpc-ds/darwin-arm64/query_templates/query14.tpl
benchbox/_binaries/tpc-ds/darwin-arm64/query_templates/query15.tpl
benchbox/_binaries/tpc-ds/darwin-arm64/query_templates/query16.tpl
benchbox/_binaries/tpc-ds/darwin-arm64/query_templates/query17.tpl
benchbox/_binaries/tpc-ds/darwin-arm64/query_templates/query18.tpl
benchbox/_binaries/tpc-ds/darwin-arm64/query_templates/query19.tpl
benchbox/_binaries/tpc-ds/darwin-arm64/query_templates/query2.tpl
benchbox/_binaries/tpc-ds/darwin-arm64/query_templates/query20.tpl
benchbox/_binaries/tpc-ds/darwin-arm64/query_templates/query21.tpl
benchbox-0.1.0.dist-info/licenses/LICENSE
benchbox-0.1.0.dist-info/METADATA
benchbox-0.1.0.dist-info/WHEEL
benchbox-0.1.0.dist-info/entry_points.txt
benchbox-0.1.0.dist-info/top_level.txt
benchbox-0.1.0.dist-info/RECORD
