Metadata-Version: 2.4
Name: benchbox
Version: 0.1.0
Summary: Embedded benchmark datasets and queries for database evaluation. Implements TPC-H, TPC-DS, TPC-DI and other industry-standard benchmarks.
Author-email: Joe Harris <joe@benchbox.dev>
License: MIT
Project-URL: Homepage, https://github.com/joeharris76/benchbox
Project-URL: Bug Tracker, https://github.com/joeharris76/benchbox/issues
Project-URL: Documentation, https://benchbox.readthedocs.io/
Project-URL: Repository, https://github.com/joeharris76/benchbox.git
Project-URL: Changelog, https://github.com/joeharris76/benchbox/blob/main/CHANGELOG.md
Keywords: benchmark,database,tpc-h,tpc-ds,tpc-di,analytics,olap,performance-testing
Classifier: Development Status :: 3 - Alpha
Classifier: Intended Audience :: Developers
Classifier: Programming Language :: Python :: 3
Classifier: Programming Language :: Python :: 3.10
Classifier: Programming Language :: Python :: 3.11
Classifier: Programming Language :: Python :: 3.12
Classifier: Programming Language :: Python :: 3.13
Classifier: Programming Language :: Python :: 3.14
Classifier: Topic :: Database
Classifier: Topic :: Software Development :: Testing :: Acceptance
Classifier: Topic :: System :: Benchmark
Requires-Python: <3.15,>=3.10
License-File: LICENSE
Requires-Dist: sqlglot>=20.0.0
Requires-Dist: click>=8.0.0
Requires-Dist: rich>=13.0.0
Requires-Dist: psutil>=5.9.0
Requires-Dist: pydantic>=2.0.0
Requires-Dist: pyyaml>=6.0.0
Requires-Dist: packaging>=24.0
Requires-Dist: jsonschema>=4.25.1
Requires-Dist: tomli>=2.0.0; python_version < "3.11"
Requires-Dist: duckdb>=1.4.0
Requires-Dist: pyarrow>=21.0.0
Requires-Dist: numpy>=1.24.0
Requires-Dist: polars>=1.36.1
Requires-Dist: clickhouse-connect>=0.10.0
Requires-Dist: psycopg2-binary>=2.9.11
Provides-Extra: dev
Requires-Dist: pytest>=8.0.0; extra == "dev"
Requires-Dist: pytest-cov>=4.1.0; extra == "dev"
Requires-Dist: pytest-benchmark>=4.0.0; extra == "dev"
Requires-Dist: pytest-xdist>=3.0.0; extra == "dev"
Requires-Dist: duckdb>=1.4.0; extra == "dev"
Requires-Dist: tox>=4.13.0; extra == "dev"
Requires-Dist: pyspark>=3.5.0; extra == "dev"
Provides-Extra: docs
Requires-Dist: sphinx>=7.2.0; extra == "docs"
Requires-Dist: furo>=2025.9.25; extra == "docs"
Requires-Dist: myst-parser>=2.0.0; extra == "docs"
Requires-Dist: sphinxcontrib-mermaid>=0.8.1; extra == "docs"
Requires-Dist: pygments>=2.18.0; extra == "docs"
Requires-Dist: sphinx-tags>=0.4.0; extra == "docs"
Requires-Dist: sphinx-design>=0.6.0; extra == "docs"
Provides-Extra: viz
Requires-Dist: plotly>=5.24.0; extra == "viz"
Requires-Dist: kaleido>=0.2.1; extra == "viz"
Requires-Dist: pandas>=2.0.0; extra == "viz"
Requires-Dist: pillow>=10.0.0; extra == "viz"
Provides-Extra: all
Requires-Dist: clickhouse-driver>=0.2.0; extra == "all"
Requires-Dist: databricks-sql-connector>=2.0.0; extra == "all"
Requires-Dist: databricks-sdk>=0.20.0; extra == "all"
Requires-Dist: databricks-connect>=14.0.0; extra == "all"
Requires-Dist: datafusion>=50.1.0; extra == "all"
Requires-Dist: pyarrow>=10.0.0; extra == "all"
Requires-Dist: firebolt-sdk>=1.18.0; extra == "all"
Requires-Dist: google-cloud-bigquery>=3.0.0; extra == "all"
Requires-Dist: google-cloud-storage>=2.0.0; extra == "all"
Requires-Dist: redshift-connector>=2.0.0; extra == "all"
Requires-Dist: snowflake-connector-python>=3.0.0; extra == "all"
Requires-Dist: trino>=0.328.0; extra == "all"
Requires-Dist: presto-python-client>=0.8.4; extra == "all"
Requires-Dist: psycopg2-binary>=2.9.0; extra == "all"
Requires-Dist: pyodbc>=4.0.0; extra == "all"
Requires-Dist: azure-identity>=1.15.0; extra == "all"
Requires-Dist: azure-storage-file-datalake>=12.14.0; extra == "all"
Requires-Dist: pyathena>=3.0.0; extra == "all"
Requires-Dist: boto3>=1.20.0; extra == "all"
Requires-Dist: cloudpathlib>=0.15.0; extra == "all"
Requires-Dist: pandas>=2.0.0; extra == "all"
Requires-Dist: chdb>=0.10.0; sys_platform != "win32" and extra == "all"
Requires-Dist: deltalake>=1.2.1; extra == "all"
Requires-Dist: pyiceberg>=0.10.0; extra == "all"
Requires-Dist: influxdb3-python>=0.10.0; extra == "all"
Requires-Dist: plotly>=5.24.0; extra == "all"
Requires-Dist: kaleido>=0.2.1; extra == "all"
Requires-Dist: pillow>=10.0.0; extra == "all"
Requires-Dist: polars>=1.35.2; extra == "all"
Requires-Dist: dask[distributed]>=2024.1.0; extra == "all"
Requires-Dist: modin[ray]>=0.32.0; extra == "all"
Requires-Dist: pyspark>=3.5.0; extra == "all"
Provides-Extra: cloud
Requires-Dist: databricks-sql-connector>=2.0.0; extra == "cloud"
Requires-Dist: databricks-sdk>=0.20.0; extra == "cloud"
Requires-Dist: firebolt-sdk>=1.18.0; extra == "cloud"
Requires-Dist: google-cloud-bigquery>=3.0.0; extra == "cloud"
Requires-Dist: google-cloud-storage>=2.0.0; extra == "cloud"
Requires-Dist: redshift-connector>=2.0.0; extra == "cloud"
Requires-Dist: snowflake-connector-python>=3.0.0; extra == "cloud"
Requires-Dist: trino>=0.328.0; extra == "cloud"
Requires-Dist: pyathena>=3.0.0; extra == "cloud"
Requires-Dist: boto3>=1.20.0; extra == "cloud"
Requires-Dist: cloudpathlib>=0.15.0; extra == "cloud"
Provides-Extra: cloudstorage
Requires-Dist: cloudpathlib>=0.15.0; extra == "cloudstorage"
Provides-Extra: clickhouse
Requires-Dist: clickhouse-driver>=0.2.0; extra == "clickhouse"
Provides-Extra: databricks
Requires-Dist: databricks-sql-connector>=2.0.0; extra == "databricks"
Requires-Dist: databricks-sdk>=0.20.0; extra == "databricks"
Requires-Dist: cloudpathlib>=0.15.0; extra == "databricks"
Provides-Extra: bigquery
Requires-Dist: google-cloud-bigquery>=3.0.0; extra == "bigquery"
Requires-Dist: google-cloud-storage>=2.0.0; extra == "bigquery"
Requires-Dist: cloudpathlib>=0.15.0; extra == "bigquery"
Provides-Extra: redshift
Requires-Dist: redshift-connector>=2.0.0; extra == "redshift"
Requires-Dist: boto3>=1.20.0; extra == "redshift"
Requires-Dist: cloudpathlib>=0.15.0; extra == "redshift"
Provides-Extra: snowflake
Requires-Dist: snowflake-connector-python>=3.0.0; extra == "snowflake"
Requires-Dist: cloudpathlib>=0.15.0; extra == "snowflake"
Provides-Extra: trino
Requires-Dist: trino>=0.328.0; extra == "trino"
Requires-Dist: cloudpathlib>=0.15.0; extra == "trino"
Provides-Extra: presto
Requires-Dist: presto-python-client>=0.8.4; extra == "presto"
Requires-Dist: cloudpathlib>=0.15.0; extra == "presto"
Provides-Extra: postgresql
Requires-Dist: psycopg2-binary>=2.9.0; extra == "postgresql"
Provides-Extra: synapse
Requires-Dist: pyodbc>=4.0.0; extra == "synapse"
Provides-Extra: fabric
Requires-Dist: pyodbc>=4.0.0; extra == "fabric"
Requires-Dist: azure-identity>=1.15.0; extra == "fabric"
Requires-Dist: azure-storage-file-datalake>=12.14.0; extra == "fabric"
Provides-Extra: athena
Requires-Dist: pyathena>=3.0.0; extra == "athena"
Requires-Dist: boto3>=1.20.0; extra == "athena"
Provides-Extra: datafusion
Requires-Dist: datafusion>=50.1.0; extra == "datafusion"
Requires-Dist: pyarrow>=10.0.0; extra == "datafusion"
Provides-Extra: firebolt
Requires-Dist: firebolt-sdk>=1.18.0; extra == "firebolt"
Requires-Dist: cloudpathlib>=0.15.0; extra == "firebolt"
Provides-Extra: influxdb
Requires-Dist: influxdb3-python>=0.10.0; extra == "influxdb"
Requires-Dist: pyarrow>=10.0.0; extra == "influxdb"
Provides-Extra: tpcdi
Requires-Dist: pandas>=2.0.0; extra == "tpcdi"
Provides-Extra: clickhouse-local
Requires-Dist: chdb>=0.10.0; sys_platform != "win32" and extra == "clickhouse-local"
Provides-Extra: table-formats
Requires-Dist: deltalake>=1.2.1; extra == "table-formats"
Requires-Dist: pyiceberg>=0.10.0; extra == "table-formats"
Provides-Extra: dataframe-pandas
Requires-Dist: pandas>=2.0.0; extra == "dataframe-pandas"
Provides-Extra: dataframe-modin
Requires-Dist: modin[ray]>=0.32.0; extra == "dataframe-modin"
Requires-Dist: pandas>=2.0.0; extra == "dataframe-modin"
Provides-Extra: dataframe-dask
Requires-Dist: dask[distributed]>=2024.1.0; extra == "dataframe-dask"
Requires-Dist: pandas>=2.0.0; extra == "dataframe-dask"
Provides-Extra: dataframe-cudf
Provides-Extra: dataframe-polars
Requires-Dist: polars>=1.35.2; extra == "dataframe-polars"
Provides-Extra: dataframe-pyspark
Requires-Dist: pyspark>=3.5.0; extra == "dataframe-pyspark"
Provides-Extra: dataframe-datafusion
Requires-Dist: datafusion>=50.1.0; extra == "dataframe-datafusion"
Provides-Extra: dataframe-pandas-family
Requires-Dist: pandas>=2.0.0; extra == "dataframe-pandas-family"
Requires-Dist: modin[ray]>=0.32.0; extra == "dataframe-pandas-family"
Requires-Dist: dask[distributed]>=2024.1.0; extra == "dataframe-pandas-family"
Provides-Extra: dataframe-expression-family
Requires-Dist: polars>=1.35.2; extra == "dataframe-expression-family"
Requires-Dist: pyspark>=3.5.0; extra == "dataframe-expression-family"
Requires-Dist: datafusion>=50.1.0; extra == "dataframe-expression-family"
Provides-Extra: dataframe-all
Requires-Dist: pandas>=2.0.0; extra == "dataframe-all"
Requires-Dist: modin[ray]>=0.32.0; extra == "dataframe-all"
Requires-Dist: dask[distributed]>=2024.1.0; extra == "dataframe-all"
Requires-Dist: polars>=1.35.2; extra == "dataframe-all"
Requires-Dist: pyspark>=3.5.0; extra == "dataframe-all"
Requires-Dist: datafusion>=50.1.0; extra == "dataframe-all"
Provides-Extra: quick-start
Requires-Dist: polars>=1.35.2; extra == "quick-start"
Provides-Extra: cloud-spark-aws
Requires-Dist: boto3>=1.34.0; extra == "cloud-spark-aws"
Provides-Extra: cloud-spark-gcp
Requires-Dist: google-cloud-dataproc>=5.0.0; extra == "cloud-spark-gcp"
Requires-Dist: google-cloud-storage>=2.0.0; extra == "cloud-spark-gcp"
Provides-Extra: cloud-spark-azure
Requires-Dist: azure-identity>=1.15.0; extra == "cloud-spark-azure"
Requires-Dist: azure-storage-file-datalake>=12.14.0; extra == "cloud-spark-azure"
Requires-Dist: requests>=2.31.0; extra == "cloud-spark-azure"
Provides-Extra: cloud-spark-snowflake
Requires-Dist: snowflake-snowpark-python>=1.11.0; extra == "cloud-spark-snowflake"
Requires-Dist: pyspark>=3.5.0; extra == "cloud-spark-snowflake"
Provides-Extra: cloud-spark-databricks
Requires-Dist: databricks-sql-connector>=2.0.0; extra == "cloud-spark-databricks"
Requires-Dist: databricks-sdk>=0.20.0; extra == "cloud-spark-databricks"
Requires-Dist: databricks-connect>=14.0.0; extra == "cloud-spark-databricks"
Requires-Dist: cloudpathlib>=0.15.0; extra == "cloud-spark-databricks"
Provides-Extra: databricks-connect
Requires-Dist: databricks-sql-connector>=2.0.0; extra == "databricks-connect"
Requires-Dist: databricks-sdk>=0.20.0; extra == "databricks-connect"
Requires-Dist: databricks-connect>=14.0.0; extra == "databricks-connect"
Requires-Dist: cloudpathlib>=0.15.0; extra == "databricks-connect"
Provides-Extra: cloud-spark
Requires-Dist: boto3>=1.34.0; extra == "cloud-spark"
Requires-Dist: google-cloud-dataproc>=5.0.0; extra == "cloud-spark"
Requires-Dist: google-cloud-storage>=2.0.0; extra == "cloud-spark"
Requires-Dist: azure-identity>=1.15.0; extra == "cloud-spark"
Requires-Dist: azure-storage-file-datalake>=12.14.0; extra == "cloud-spark"
Requires-Dist: requests>=2.31.0; extra == "cloud-spark"
Requires-Dist: snowflake-snowpark-python>=1.11.0; extra == "cloud-spark"
Requires-Dist: pyspark>=3.5.0; extra == "cloud-spark"
Requires-Dist: databricks-sql-connector>=2.0.0; extra == "cloud-spark"
Requires-Dist: databricks-sdk>=0.20.0; extra == "cloud-spark"
Requires-Dist: databricks-connect>=14.0.0; extra == "cloud-spark"
Requires-Dist: cloudpathlib>=0.15.0; extra == "cloud-spark"
Provides-Extra: mcp
Requires-Dist: mcp>=1.2.0; extra == "mcp"
Provides-Extra: spark
Requires-Dist: pyspark>=4.0.1; extra == "spark"
Dynamic: license-file
